[{"homescore":136,"awayscore":59,"hometeam":"Port Adelaide","awayteam":"Brisbane Lions","chanceofresult":81.0,"date":"Sunday 08 May 2016 04:10 PM"},{"homescore":75,"awayscore":82,"hometeam":"St Kilda","awayteam":"North Melbourne","chanceofresult":89.2,"date":"Sunday 08 May 2016 03:20 PM"},{"homescore":77,"awayscore":95,"hometeam":"Fremantle","awayteam":"GWS Giants","chanceofresult":99.2,"date":"Sunday 08 May 2016 06:10 PM"},{"homescore":123,"awayscore":108,"hometeam":"Western Bulldogs","awayteam":"Adelaide Crows","chanceofresult":66.0,"date":"Saturday 07 May 2016 07:40 PM"},{"homescore":87,"awayscore":160,"hometeam":"Gold Coast Suns","awayteam":"Melbourne","chanceofresult":57.4,"date":"Saturday 07 May 2016 05:10 PM"},{"homescore":135,"awayscore":54,"hometeam":"Sydney Swans","awayteam":"Essendon","chanceofresult":99.5,"date":"Saturday 07 May 2016 04:35 PM"},{"homescore":123,"awayscore":79,"hometeam":"Geelong Cats","awayteam":"West Coast Eagles","chanceofresult":81.2,"date":"Saturday 07 May 2016 02:10 PM"},{"homescore":84,"awayscore":99,"hometeam":"Collingwood","awayteam":"Carlton","chanceofresult":46.2,"date":"Saturday 07 May 2016 01:45 PM"},{"homescore":90,"awayscore":136,"hometeam":"Richmond","awayteam":"Hawthorn","chanceofresult":74.6,"date":"Friday 06 May 2016 07:50 PM"}]