[{"hometeam":"Collingwood","awayteam":"Geelong Cats","drawchance":0.1,"awaychance":97.8,"date":"Saturday 21 May 2016 01:45 PM","homechance":2.1},{"hometeam":"Gold Coast Suns","awayteam":"Adelaide Crows","drawchance":1.4000000000000001,"awaychance":86.7,"date":"Saturday 21 May 2016 02:10 PM","homechance":11.899999999999999},{"hometeam":"Port Adelaide","awayteam":"West Coast Eagles","drawchance":1.6,"awaychance":82.1,"date":"Saturday 21 May 2016 04:05 PM","homechance":16.3},{"hometeam":"North Melbourne","awayteam":"Carlton","drawchance":1.0999999999999999,"awaychance":7.9,"date":"Saturday 21 May 2016 07:25 PM","homechance":91.0},{"hometeam":"Fremantle","awayteam":"Richmond","drawchance":2.3,"awaychance":56.39999999999999,"date":"Saturday 21 May 2016 05:40 PM","homechance":41.3},{"hometeam":"Melbourne","awayteam":"Brisbane Lions","drawchance":0.7000000000000001,"awaychance":2.5,"date":"Sunday 22 May 2016 01:10 PM","homechance":96.8},{"hometeam":"GWS Giants","awayteam":"Western Bulldogs","drawchance":2.4,"awaychance":37.2,"date":"Sunday 22 May 2016 03:20 PM","homechance":60.4},{"hometeam":"St Kilda","awayteam":"Essendon","drawchance":2.4,"awaychance":24.4,"date":"Sunday 22 May 2016 04:40 PM","homechance":73.2},{"hometeam":"Sydney Swans","awayteam":"North Melbourne","drawchance":2.9000000000000004,"awaychance":30.3,"date":"Friday 27 May 2016 07:50 PM","homechance":66.8}]