[{"name":"Brumbies","lastgame":"W 65-5 v SUN","wdl":"8-96-4","averageseed":1.132025,"positionchance":{"4":0.0,"5":0.0,"1":86.86,"2":13.0775,"3":0.0625},"rpi":0.2752764921710234,"prem-pts":226,"elorank":18,"nextgame":"1/7 v RED","points-difference":90,"try-bonus":2,"bonus-points":2,"rpirank":4,"elo":2048,"top4chance":86.8575,"losing-bonus":0,"finalschance":97.4425},{"name":"Waratahs","lastgame":"W 45-25 v CHI","wdl":"7-96-5","averageseed":1.8782,"positionchance":{"4":0.0,"5":0.0,"1":13.125,"2":85.92999999999999,"3":0.9450000000000001},"rpi":0.27019725427928554,"prem-pts":226,"elorank":18,"nextgame":"2/7 @ SUN","points-difference":68,"try-bonus":3,"bonus-points":6,"rpirank":8,"elo":2034,"top4chance":13.2975,"losing-bonus":3,"finalschance":61.26},{"name":"Rebels","lastgame":"W 27-22 v FOR","wdl":"6-96-6","averageseed":3.0036,"positionchance":{"4":1.3825,"5":0.0,"1":0.015,"2":0.9924999999999999,"3":97.61},"rpi":0.24905561018842265,"prem-pts":219,"elorank":18,"nextgame":"2/7 v STO","points-difference":-39,"try-bonus":2,"bonus-points":3,"rpirank":11,"elo":1988,"top4chance":0.015000000000000001,"losing-bonus":1,"finalschance":0.16},{"name":"Reds","lastgame":"W 35-25 v SUN","wdl":"3-97-8","averageseed":4.01665,"positionchance":{"4":95.57,"5":3.0475,"1":0.0,"2":0.0,"3":1.3825},"rpi":0.246088781733313,"prem-pts":208,"elorank":18,"nextgame":"1/7 @ BRU","points-difference":-101,"try-bonus":0,"bonus-points":2,"rpirank":12,"elo":1941,"top4chance":0.0,"losing-bonus":2,"finalschance":0.0},{"name":"Force","lastgame":"L 22-27 @ REB","wdl":"2-96-10","averageseed":4.969525,"positionchance":{"4":3.0475,"5":96.9525,"1":0.0,"2":0.0,"3":0.0},"rpi":0.25698134692275315,"prem-pts":204,"elorank":18,"nextgame":"2/7 @ CHE","points-difference":-147,"try-bonus":0,"bonus-points":4,"rpirank":10,"elo":1896,"top4chance":0.0,"losing-bonus":4,"finalschance":0.0}]